{
  "$schema": "http://json-schema.org/draft-04/schema#",
  "id": "http://judkins.house/apis/k2/v1/canalFabricNetworkVxlan.json",
  "$$target": "canalFabricNetworkVxlan.json",
  "title": "Canal Fabric VXLan Network configuration",
  "description": "Canal Fabric VXLan Network configuration.",

  "properties": {
    "type": {
      "description": "Indicates that it is vxlan.",
      "enum": [ "vxlan" ],
      "type": "string",
      "default": "vxlan"
    }
  },
  "required": [
    "type"
  ],
  "additionalProperties": false,
  "type": "object"
}
